Metadata-Version: 1.1
Name: competitive-dl
Version: 1.0.0
Summary: Download any problem/problem set from any contest/archives from any competitive website as PDF !
Home-page: https://github.com/shravan97/competitive-dl
Author: Shravan Murali
Author-email: shravanmurali@gmail.com
License: MIT License
Keywords: downloader,download as pdf,competitive programming,competitive,cli
Platform: UNKNOWN
Classifier: Operating System :: POSIX :: Linux
Classifier: License :: OSI Approved :: MIT License
Classifier: Programming Language :: Python :: 2.7
Classifier: Topic :: Education
